{
    "Haryanto": 238,
    "Syahrul": 231,
    "Christian's Hornie": 220,
    "Petrobras Williams RBS F1": 216,
    "Uncle Moe's Family Speedbag": 214,
    "Johnny UniHaas": 210,
    "Toasted eggs": 206,
    "Peugeot Over Ford": 206,
    "BMW Should Be Here": 205,
    "Make A U Turn": 204,
    "My Fav'rit Colour Is Blue": 203,
    "Bwoah Moet Shell Racing": 202,
    "Matty's snipped balls": 201,
    "Telefonica Minardi Doimo": 198,
    "Lights out, got punched": 198,
    "Josh's hairy balls": 197,
    "Gelael": 197,
    "One Red Bull Car & Gasly": 196,
    "Denso Panasonic Toyota F1": 196,
    "Hesketh 2.1": 193,
    "Stuart's snipped balls": 191,
    "BMW Motorrad": 187,
    "The Lizard Queen": 173,
    "Mirror, Signal, Manoeuvre": 172,
    "Squeshed Nintendo Racing": 168,
    "A Little Team": 166,
    "Ferrari Champions 2026": 165,
    "THE LONG AND WINDING ROAD": 163,
    "Push To Pass": 159,
    "Maxy & The Boys": 157,
    "Just win init": 155,
    "kicktwitchyoutubepremium": 151,
    "Forced to pick Max": 150,
    "Bwoah OnlyFans VIP Racing": 149,
    "Mater's Mates": 148,
    "Les eclairs": 147,
    "Lightning McCars": 146,
    "An Oscar for breakfast": 146,
    "Throw Him In JaYaL": 138,
    "JPS Lotus Renault": 135,
    "Dinoco Piston Champions": 135,
    "Siemens McLaren West": 129,
    "Grazzi#44": 129,
    "A Sauber or Kick or Stake": 129,
    "Hawks at T2": 126,
    "Vodafone Ferrari Marlboro": 120,
    "O B Latte": 110,
    "E l'ora del martello": 106,
    "Better Luck Next Time Bud": 102,
    "Haas every name ben taken": 94,
    "Go Boys Give Us Nothing": 94,
    "Ms Fritters Driving Skool": 93,
    "I simp for Zak Brown": 92,
    "No Horners Club": 91,
    "Mc Sled Dogs": 89,
    "Ferrari Strategists": 49,
    "sBinnala Yacht Club": 48,
    "The Big One": 47,
    "Lee Carvallo's F1 Challen": 46,
    "Bwoah Rolex Sipsmith Golf": 44,
    "Racing No Points": 40
}