{
    "Position": "Name",
    "Race": [
        "Australia"
    ],
    "Team Name": [
        "The Stopwatch Never Lies"
    ],
    "Driver 1": [
        "Russell"
    ],
    "Driver 2": [
        "Alonso"
    ],
    "Driver 3": [
        "Albon"
    ],
    "Driver 4": [
        "Sainz"
    ],
    "Driver 5": [
        "Gasly"
    ],
    "Constructor 1": [
        "Red Bull"
    ],
    "Constructor 2": [
        "Alpine"
    ],
    "DRS Boost": [
        "Russell"
    ],
    "Penalties": [
        0
    ],
    "Extra DRS": [
        0
    ],
    "Perks": [
        "None"
    ]
}
