{
    "Driver Points": {
        "Ocon": [
            7,
            8,
            0,
            5,
            12,
            11
        ],
        "Gasly": [
            6,
            -20,
            5,
            5,
            13,
            15
        ],
        "Stroll": [
            8,
            -17,
            16,
            13,
            9,
            -19
        ],
        "Alonso": [
            7,
            16,
            9,
            14,
            15,
            9
        ],
        "Leclerc": [
            22,
            37,
            38,
            31,
            34,
            33
        ],
        "Sainz": [
            36,
            0,
            46,
            28,
            30,
            26
        ],
        "Bearman": [
            0,
            26,
            0,
            0,
            0,
            0
        ],
        "Magnussen": [
            7,
            7,
            8,
            9,
            17,
            1
        ],
        "Hulkenberg": [
            -3,
            9,
            11,
            10,
            4,
            13
        ],
        "Bottas": [
            0,
            -1,
            2,
            8,
            -14,
            10
        ],
        "Guanyu": [
            11,
            -2,
            4,
            -17,
            13,
            20
        ],
        "Norris": [
            16,
            8,
            23,
            19,
            36,
            25
        ],
        "Piastri": [
            10,
            23,
            21,
            10,
            12,
            22
        ],
        "Hamilton": [
            12,
            6,
            -19,
            5,
            30,
            20
        ],
        "Russell": [
            20,
            15,
            -3,
            13,
            27,
            10
        ],
        "Tsunoda": [
            -1,
            -1,
            11,
            10,
            -6,
            23
        ],
        "Ricciardo": [
            5,
            0,
            8,
            -19,
            -9,
            16
        ],
        "Verstappen": [
            45,
            36,
            -10,
            47,
            58,
            40
        ],
        "Perez": [
            31,
            31,
            22,
            33,
            40,
            30
        ],
        "Albon": [
            0,
            6,
            4,
            -20,
            11,
            10
        ],
        "Sargeant": [
            3,
            7,
            0,
            9,
            8,
            -7
        ]
    },
    "Driver Values": {
        "Ocon": [
            7.8,
            8.3,
            8.8,
            8.6,
            8.5,
            9.0
        ],
        "Gasly": [
            7.8,
            7.7,
            7.5,
            7.4,
            7.3,
            8.0
        ],
        "Stroll": [
            10.7,
            11.2,
            11.0,
            12.0,
            12.5,
            13.0
        ],
        "Alonso": [
            15.8,
            15.9,
            16.2,
            16.3,
            16.4,
            16.5
        ],
        "Leclerc": [
            19.1,
            19.4,
            20.4,
            21.4,
            21.7,
            22.0
        ],
        "Sainz": [
            18.5,
            0,
            19.8,
            19.8,
            20.1,
            20.4
        ],
        "Bearman": [
            0,
            14.0,
            0,
            0,
            0,
            0
        ],
        "Magnussen": [
            6.2,
            6.7,
            7.2,
            7.7,
            8.2,
            8.7
        ],
        "Hulkenberg": [
            6.4,
            6.2,
            6.7,
            7.2,
            7.7,
            7.6
        ],
        "Bottas": [
            6.4,
            6.2,
            6.0,
            5.9,
            6.4,
            6.2
        ],
        "Guanyu": [
            6.6,
            7.1,
            6.9,
            6.8,
            6.6,
            7.1
        ],
        "Norris": [
            23.0,
            23.1,
            23.2,
            23.5,
            23.8,
            24.1
        ],
        "Piastri": [
            19.0,
            19.1,
            19.4,
            19.7,
            19.8,
            19.9
        ],
        "Hamilton": [
            19.3,
            19.4,
            19.5,
            19.0,
            18.7,
            19.0
        ],
        "Russell": [
            18.8,
            19.1,
            19.2,
            18.7,
            18.8,
            19.1
        ],
        "Tsunoda": [
            8.0,
            7.8,
            7.6,
            8.1,
            8.6,
            8.4
        ],
        "Ricciardo": [
            9.0,
            8.9,
            8.7,
            9.2,
            9.0,
            8.8
        ],
        "Verstappen": [
            30.0,
            30.2,
            30.4,
            29.7,
            29.9,
            30.1
        ],
        "Perez": [
            20.8,
            21.2,
            22.1,
            22.4,
            22.7,
            23.0
        ],
        "Albon": [
            7.0,
            6.8,
            7.3,
            7.2,
            7.2,
            7.5
        ],
        "Sargeant": [
            5.5,
            5.4,
            5.9,
            5.9,
            6.4,
            5.9
        ]
    },
    "Team Points": {
        "Alpine": [
            12,
            -13,
            6,
            11,
            28,
            29
        ],
        "Aston Martin": [
            20,
            9,
            35,
            32,
            29,
            -7
        ],
        "Ferrari": [
            73,
            58,
            92,
            59,
            74,
            79
        ],
        "Haas": [
            9,
            19,
            20,
            20,
            26,
            19
        ],
        "Kick Sauber": [
            10,
            -4,
            7,
            -8,
            4,
            29
        ],
        "McLaren": [
            36,
            41,
            54,
            39,
            48,
            50
        ],
        "Mercedes": [
            42,
            36,
            -17,
            28,
            62,
            40
        ],
        "RB": [
            7,
            4,
            24,
            -4,
            -14,
            44
        ],
        "Red Bull": [
            89,
            90,
            32,
            108,
            126,
            85
        ],
        "Williams": [
            4,
            14,
            5,
            -10,
            20,
            4
        ]
    },
    "Team Values": {
        "Alpine": [
            6.4,
            8.3,
            8.1,
            8.0,
            7.9,
            8.4
        ],
        "Aston Martin": [
            13.6,
            14.1,
            14.0,
            14.5,
            15.0,
            15.1
        ],
        "Ferrari": [
            19.3,
            19.6,
            19.9,
            20.9,
            21.2,
            21.5
        ],
        "Haas": [
            6.3,
            6.2,
            6.7,
            7.2,
            7.7,
            8.2
        ],
        "Kick Sauber": [
            6.6,
            6.5,
            6.3,
            6.2,
            6.0,
            5.9
        ],
        "McLaren": [
            23.2,
            23.3,
            23.6,
            23.9,
            24.0,
            24.1
        ],
        "Mercedes": [
            20.1,
            20.2,
            20.3,
            19.8,
            19.9,
            20.2
        ],
        "RB": [
            8.5,
            8.4,
            8.3,
            8.8,
            8.6,
            8.4
        ],
        "Red Bull": [
            27.9,
            28.0,
            28.2,
            28.2,
            28.4,
            28.6
        ],
        "Williams": [
            6.3,
            6.2,
            6.7,
            6.6,
            6.4,
            6.3
        ]
    }
}
