{
    "Bahrain": {
        "Driver 1": "Sainz",
        "Driver 2": "Verstappen",
        "Driver 3": "Albon",
        "Driver 4": "Gasly",
        "Driver 5": "Ricciardo",
        "Constructor 1": "Ferrari",
        "Constructor 2": "Williams",
        "DRS Boost": "Verstappen",
        "Penalties": 0,
        "Perks": "None"
    },
    "Saudi Arabia": {
        "Driver 1": "Leclerc",
        "Driver 2": "Verstappen",
        "Driver 3": "Albon",
        "Driver 4": "Gasly",
        "Driver 5": "Ricciardo",
        "Constructor 1": "Ferrari",
        "Constructor 2": "Williams",
        "DRS Boost": "Verstappen",
        "Penalties": 0,
        "Perks": "None"
    },
    "Australia": {
        "Driver 1": "Leclerc",
        "Driver 2": "Verstappen",
        "Driver 3": "Albon",
        "Driver 4": "Hulkenberg",
        "Driver 5": "Ricciardo",
        "Constructor 1": "Ferrari",
        "Constructor 2": "RB",
        "DRS Boost": "Verstappen",
        "Penalties": 0,
        "Perks": "None"
    },
    "Japan": {
        "Driver 1": "Leclerc",
        "Driver 2": "Verstappen",
        "Driver 3": "Albon",
        "Driver 4": "Hulkenberg",
        "Driver 5": "Ricciardo",
        "Constructor 1": "Ferrari",
        "Constructor 2": "RB",
        "DRS Boost": "Verstappen",
        "Penalties": 0,
        "Perks": "None"
    },
    "China": {
        "Driver 1": "Leclerc",
        "Driver 2": "Verstappen",
        "Driver 3": "Albon",
        "Driver 4": "Hulkenberg",
        "Driver 5": "Ricciardo",
        "Constructor 1": "Ferrari",
        "Constructor 2": "RB",
        "DRS Boost": "Verstappen",
        "Penalties": 0,
        "Perks": "None"
    },
    "Miami": {
        "Driver 1": "Leclerc",
        "Driver 2": "Verstappen",
        "Driver 3": "Albon",
        "Driver 4": "Hulkenberg",
        "Driver 5": "Ricciardo",
        "Constructor 1": "Ferrari",
        "Constructor 2": "RB",
        "DRS Boost": "Verstappen",
        "Penalties": 0,
        "Perks": "None"
    },
    "Emilia Romagna": {
        "Driver 1": "Leclerc",
        "Driver 2": "Verstappen",
        "Driver 3": "Albon",
        "Driver 4": "Hulkenberg",
        "Driver 5": "Ricciardo",
        "Constructor 1": "Ferrari",
        "Constructor 2": "RB",
        "DRS Boost": "Verstappen",
        "Penalties": 0,
        "Perks": "None"
    },
    "Monaco": {
        "Driver 1": "Leclerc",
        "Driver 2": "Verstappen",
        "Driver 3": "Albon",
        "Driver 4": "Hulkenberg",
        "Driver 5": "Ricciardo",
        "Constructor 1": "Ferrari",
        "Constructor 2": "RB",
        "DRS Boost": "Verstappen",
        "Penalties": 0,
        "Perks": "None"
    },
    "Canada": {
        "Driver 1": "Leclerc",
        "Driver 2": "Verstappen",
        "Driver 3": "Albon",
        "Driver 4": "Hulkenberg",
        "Driver 5": "Ricciardo",
        "Constructor 1": "Ferrari",
        "Constructor 2": "RB",
        "DRS Boost": "Verstappen",
        "Penalties": 0,
        "Perks": "None"
    },
    "Spain": {
        "Driver 1": "Leclerc",
        "Driver 2": "Verstappen",
        "Driver 3": "Albon",
        "Driver 4": "Hulkenberg",
        "Driver 5": "Ricciardo",
        "Constructor 1": "Ferrari",
        "Constructor 2": "RB",
        "DRS Boost": "Verstappen",
        "Penalties": 0,
        "Perks": "None"
    }
}
